mlb_fantasy/__init__.py
mlb_fantasy/fantasy_mlb.py
mlb_fantasy/main.py
mlb_fantasy-1.1.dist-info/METADATA
mlb_fantasy-1.1.dist-info/WHEEL
mlb_fantasy-1.1.dist-info/entry_points.txt
mlb_fantasy-1.1.dist-info/top_level.txt
mlb_fantasy-1.1.dist-info/RECORD
